english_asr/conformer.py
english_asr-1.2.dist-info/LICENSE
english_asr-1.2.dist-info/METADATA
english_asr-1.2.dist-info/WHEEL
english_asr-1.2.dist-info/top_level.txt
english_asr-1.2.dist-info/RECORD
